HexoDoc/README.md
HexoDoc/__init__.py
HexoDoc/__main__.py
HexoDoc/file.epub
HexoDoc/index.html
HexoDoc/css/__init__.py
HexoDoc/css/annotations.css
HexoDoc/css/main.css
HexoDoc/css/normalize.css
HexoDoc/css/popup.css
HexoDoc/font/__init__.py
HexoDoc/font/fontello.eot
HexoDoc/font/fontello.svg
HexoDoc/font/fontello.ttf
HexoDoc/font/fontello.woff
HexoDoc/img/__init__.py
HexoDoc/img/annotator-glyph-sprite.png
HexoDoc/img/annotator-icon-sprite.png
HexoDoc/img/apple-touch-icon.png
HexoDoc/img/cancelfullscreen.png
HexoDoc/img/close.png
HexoDoc/img/fullscreen.png
HexoDoc/img/loader.gif
HexoDoc/img/menu-icon.png
HexoDoc/img/save.png
HexoDoc/img/saved.png
HexoDoc/img/settings-s.png
HexoDoc/img/settings.png
HexoDoc/img/star.png
HexoDoc/js/__init__.py
HexoDoc/js/epub.js
HexoDoc/js/epub.min.js
HexoDoc/js/epub.min.map
HexoDoc/js/hooks.min.js
HexoDoc/js/hooks.min.map
HexoDoc/js/reader.js
HexoDoc/js/reader.js.map
HexoDoc/js/reader.min.js
HexoDoc/js/reader.min.map
HexoDoc/js/hooks/__init__.py
HexoDoc/js/hooks/extensions/__init__.py
HexoDoc/js/hooks/extensions/highlight.js
HexoDoc/js/libs/__init__.py
HexoDoc/js/libs/jquery.min.js
HexoDoc/js/libs/localforage.min.js
HexoDoc/js/libs/screenfull.js
HexoDoc/js/libs/screenfull.min.js
HexoDoc/js/libs/zip.min.js
HexoDoc/js/plugins/__init__.py
HexoDoc/js/plugins/hypothesis.js
HexoDoc/js/plugins/search.js
hexo_doc-2024.3.1.0.dist-info/METADATA
hexo_doc-2024.3.1.0.dist-info/WHEEL
hexo_doc-2024.3.1.0.dist-info/entry_points.txt
hexo_doc-2024.3.1.0.dist-info/top_level.txt
hexo_doc-2024.3.1.0.dist-info/RECORD
